senf/__init__.py
senf/__init__.pyi
senf/_argv.py
senf/_compat.py
senf/_environ.py
senf/_fsnative.py
senf/_print.py
senf/_stdlib.py
senf/_temp.py
senf/_winansi.py
senf/_winapi.py
senf/py.typed
senf-1.5.0.dist-info/LICENSE
senf-1.5.0.dist-info/METADATA
senf-1.5.0.dist-info/WHEEL
senf-1.5.0.dist-info/top_level.txt
senf-1.5.0.dist-info/RECORD
